{
  "generated": "2026-05-15T14:35:36.896517+00:00",
  "generated_hst": "2026-05-15 04:35 HST",
  "kilauea_notices": [
    {
      "title": "HAWAIIAN VOLCANO OBSERVATORY STATUS REPORT",
      "date": "2026-05-15",
      "alert_level": "ADVISORY",
      "color_code": "YELLOW",
      "message": "HVO Kilauea YELLOW/ADVISORY - Episode 47 of the ongoing Halema\u02bbuma\u02bbu eruption at the summit of K\u012blauea ended abruptly at 12:27 a.m. HST on May 15. The eruption is currently paused.",
      "url": "https://vhptools.usgs.gov/hans2//hans2/view/notice/DOI-USGS-HVO-2026-05-15T10:42:06+00:00",
      "notice_type": "Status Report"
    }
  ],
  "mauna_loa_notices": [
    {
      "title": "HAWAIIAN VOLCANO OBSERVATORY MONTHLY UPDATE",
      "date": "2026-05-07",
      "alert_level": "NORMAL",
      "color_code": "GREEN",
      "message": "HVO Haleakala GREEN/NORMAL - No activity of concern for Haleakal\u0101.",
      "url": "https://vhptools.usgs.gov/hans2//hans2/view/notice/DOI-USGS-HVO-2026-05-07T19:16:53+00:00",
      "notice_type": "Monthly Update"
    }
  ]
}